django_filtering/__init__.py
django_filtering/apps.py
django_filtering/filter.py
django_filtering/models.py
django_filtering/settings.py
django_filtering/tests/__init__.py
django_filtering/tests/test_filter_mapping.py
django_filtering/tests/test_filtering.py
ts_django_filtering-1.1.0.dist-info/METADATA
ts_django_filtering-1.1.0.dist-info/WHEEL
ts_django_filtering-1.1.0.dist-info/licenses/LICENSE
ts_django_filtering-1.1.0.dist-info/RECORD
