Metadata-Version: 2.4
Name: ts-django-filtering
Version: 1.1.0
Summary: TechServ in-house ORM model attribute filtering
Author-email: TechServ Engineering Team <developers@techservltd.onmicrosoft.com>
License-Expression: MIT
License-File: LICENSE
Requires-Python: >=3.12
Requires-Dist: django==5.*
